<Properties StartupConfiguration="{CE87210F-5194-4201-801F-BD0D8EA92801}|Default">
  <MonoDevelop.Ide.Workbench>
    <Pads>
      <Pad Id="ProjectPad">
        <State name="__root__">
          <Node name="poker-6000" expanded="True" selected="True" />
        </State>
      </Pad>
      <Pad Id="MonoDevelop.UnitTesting.TestPad">
        <State name="__root__">
          <Node name="poker-6000" expanded="True" selected="True" />
        </State>
      </Pad>
    </Pads>
  </MonoDevelop.Ide.Workbench>
  <MonoDevelop.Ide.DebuggingService.PinnedWatches />
  <MonoDevelop.Ide.ItemProperties.poker-6000 PreferredExecutionTarget="MonoDevelop.IPhone.IPhoneSimulatorTarget.9168F5CF-DF4A-4F92-84BE-8F7A29A653BD" />
  <MonoDevelop.Ide.Workspace ActiveConfiguration="Debug|iPhoneSimulator" />
  <MonoDevelop.Ide.DebuggingService.Breakpoints>
    <BreakpointStore />
  </MonoDevelop.Ide.DebuggingService.Breakpoints>
  <MultiItemStartupConfigurations />
</Properties>